pynwb-src/__init__.py
pynwb-src/simulation_output.py
pynwb-src/test.py
src/__init__.py
src/create_extension_spec.py
nwbext_simulation_output-0.1.dist-info/METADATA
nwbext_simulation_output-0.1.dist-info/WHEEL
nwbext_simulation_output-0.1.dist-info/top_level.txt
nwbext_simulation_output-0.1.dist-info/RECORD
