Metadata-Version: 2.1
Name: nwbext-simulation-output
Version: 0.1
Summary: Extension for storing large-scale simulation output in the Neurodata Without Borders: Neurophysiology format
Home-page: UNKNOWN
Author: Ben Dichter
Author-email: ben.dichter@gmail.com
License: UNKNOWN
Keywords: nwb,extension
Platform: UNKNOWN
Requires-Dist: pynwb
Requires-Dist: hdmf
Requires-Dist: numpy
